pymitter/__init__.py
pymitter/py.typed
pymitter-1.1.3.dist-info/METADATA
pymitter-1.1.3.dist-info/WHEEL
pymitter-1.1.3.dist-info/licenses/LICENSE
pymitter-1.1.3.dist-info/RECORD
