Metadata-Version: 2.4
Name: pymitter
Version: 1.1.3
Summary: Python port of the extended Node.js EventEmitter 2 approach providing namespaces, wildcards and TTL.
Project-URL: Homepage, https://github.com/riga/pymitter
Project-URL: Documentation, https://pymitter.readthedocs.io
Project-URL: Repository, https://github.com/riga/pymitter.git
Project-URL: Bug Tracker, https://github.com/riga/pymitter/issues
Project-URL: Changelog, https://github.com/riga/pymitter/releases
Author-email: Marcel Rieger <github.riga@icloud.com>
License-Expression: BSD-3-Clause
License-File: LICENSE
Keywords: emitter,event,eventemitter,node,nodejs,wildcard
Classifier: Intended Audience :: Developers
Classifier: Intended Audience :: Information Technology
Classifier: Intended Audience :: Science/Research
Classifier: License :: OSI Approved :: BSD License
Classifier: Operating System :: OS Independent
Classifier: Programming Language :: Python
Classifier: Programming Language :: Python :: 3
Classifier: Programming Language :: Python :: 3.9
Classifier: Programming Language :: Python :: 3.10
Classifier: Programming Language :: Python :: 3.11
Classifier: Programming Language :: Python :: 3.12
Classifier: Programming Language :: Python :: 3.13
Requires-Python: >=3.9
Requires-Dist: typing-extensions~=4.14.1
